QASolver.py
README.md
setup.py
QASolver.egg-info/PKG-INFO
QASolver.egg-info/SOURCES.txt
QASolver.egg-info/dependency_links.txt
QASolver.egg-info/top_level.txt